Metadata-Version: 2.1
Name: decoil
Version: 1.1.3
Summary: EcDNA reconstruction from long-read nanopore data
Author: Madalina Giurgiu
Author-email: giurgiumadalina25@gmail.com
License: MIT
Requires-Python: >=3.10.0
License-File: LICENSE
Requires-Dist: biopython==1.80
Requires-Dist: intervaltree==3.1.0
Requires-Dist: matplotlib==3.5.0
Requires-Dist: mosek==10.1.21
Requires-Dist: nanomath==1.3.0
Requires-Dist: networkx==2.5.1
Requires-Dist: numpy==1.23
Requires-Dist: overrides==7.4.0
Requires-Dist: pandas==2.2.3
Requires-Dist: pulp==2.7.0
Requires-Dist: pyBigWig==0.3.22
Requires-Dist: pybedtools==0.9.0
Requires-Dist: pysam==0.21.0
Requires-Dist: scikit-learn==1.3.2
Requires-Dist: scipy==1.8
Requires-Dist: seaborn==0.13.0
Requires-Dist: setuptools==68.2.2
Requires-Dist: snakemake==7.32.4
Requires-Dist: vcfpy==0.13.8
Requires-Dist: bionumpy==1.0.12
Requires-Dist: nanomonsv==0.7.2
Requires-Dist: configparser==7.1.0
Requires-Dist: svim==2.0.0
Requires-Dist: cuteSV==2.1.1
Requires-Dist: cython==3.0.11
Requires-Dist: parasail==1.3.4
